LICENSE
README.md
setup.py
twitter_scraper_in/__init__.py
twitter_scraper_in.egg-info/PKG-INFO
twitter_scraper_in.egg-info/SOURCES.txt
twitter_scraper_in.egg-info/dependency_links.txt
twitter_scraper_in.egg-info/requires.txt
twitter_scraper_in.egg-info/top_level.txt