Metadata-Version: 2.1
Name: twitter-scraper-in
Version: 1.0.0
Summary: A python library to scrape twitter followers.
Home-page: UNKNOWN
Author: DataKund
Author-email: datakund@gmail.com
License: Apache License 2.0
Keywords: twitter tweet followers python bot_studio automation search scraper scrape follower following profile posts like comment
Platform: UNKNOWN
License-File: LICENSE
